.gitignore
AUTHORS.txt
CHANGES.rst
COPYING.txt
MANIFEST.in
README.rst
run_tests.sh
setup.py
etc/karaage-cluster-tools.cfg
karaage_cluster_tools/__init__.py
karaage_cluster_tools/version.py
karaage_cluster_tools.egg-info/PKG-INFO
karaage_cluster_tools.egg-info/SOURCES.txt
karaage_cluster_tools.egg-info/dependency_links.txt
karaage_cluster_tools.egg-info/requires.txt
karaage_cluster_tools.egg-info/top_level.txt
sbin/kg-send-usage