Metadata-Version: 1.1
Name: karaage-cluster-tools
Version: 1.2.6
Summary: Karaage cluster management tools
Home-page: https://github.com/Karaage-Cluster/karaage-cluster-tools
Author: Brian May
Author-email: brian@linuxpenguins.xyz
License: GPL3+
Keywords: karaage
Platform: UNKNOWN
Classifier: Development Status :: 5 - Production/Stable
Classifier: Intended Audience :: Developers
Classifier: License :: OSI Approved :: GNU General Public License v3 or later (GPLv3+)
Classifier: Operating System :: OS Independent
Classifier: Programming Language :: Python :: 2.7
Classifier: Programming Language :: Python :: 3.4
Classifier: Programming Language :: Python :: 3.5
Classifier: Topic :: Software Development :: Libraries :: Python Modules
